acid/__init__.py
acid/acid.py
acid/public/test_data.json
acid/static/css/acid.css
acid/static/html/acid.html.mako
acid/static/html/acid_parent.html.mako
acid/static/html/aside.html.mako
acid/static/html/scope_storage_test.html
acid/static/js/acid.js
acid/static/js/acid_parent.js
acid/static/js/acid_update_status.js
acid/static/js/jquery.ajaxq-0.0.1.js
acid_xblock-0.4.1.dist-info/AUTHORS
acid_xblock-0.4.1.dist-info/LICENSE.TXT
acid_xblock-0.4.1.dist-info/METADATA
acid_xblock-0.4.1.dist-info/WHEEL
acid_xblock-0.4.1.dist-info/entry_points.txt
acid_xblock-0.4.1.dist-info/top_level.txt
acid_xblock-0.4.1.dist-info/RECORD
