Metadata-Version: 2.1
Name: acid-xblock
Version: 0.4.1
Summary: Acid XBlock Test
Home-page: https://github.com/openedx/acid-block
Author: edX
Author-email: oscm@edx.org
Classifier: Development Status :: 4 - Beta
Classifier: Intended Audience :: Developers
Classifier: License :: OSI Approved :: GNU Affero General Public License v3
Classifier: Natural Language :: English
Classifier: Programming Language :: Python :: 3
Classifier: Programming Language :: Python :: 3.11
Classifier: Programming Language :: Python :: 3.12
License-File: LICENSE.TXT
License-File: AUTHORS
Requires-Dist: Mako
Requires-Dist: XBlock
Requires-Dist: lazy
